ListMaster/__init__.py
ListMaster/list_filter.py
ListMaster/list_modification.py
ListMaster/list_search.py
ListMaster/list_sorting.py
ListMaster/list_statistics.py
ListMaster/list_unique.py
ListMaster-0.1.5.dist-info/METADATA
ListMaster-0.1.5.dist-info/WHEEL
ListMaster-0.1.5.dist-info/top_level.txt
ListMaster-0.1.5.dist-info/RECORD
