Metadata-Version: 2.1
Name: ListMaster
Version: 0.1.5
Summary: ListMaster pengolah list python
Home-page: https://github.com/Dwi-Wahyu/ListMaster.git
Author: Kelompok 1
